.gitignore
.pylintrc
LICENSE
README.md
requirements.txt
setup.cfg
setup.py
api_dog_json_v2_parser.egg-info/PKG-INFO
api_dog_json_v2_parser.egg-info/SOURCES.txt
api_dog_json_v2_parser.egg-info/dependency_links.txt
api_dog_json_v2_parser.egg-info/entry_points.txt
api_dog_json_v2_parser.egg-info/requires.txt
api_dog_json_v2_parser.egg-info/top_level.txt
api_dog_parser_v2/__init__.py
api_dog_parser_v2/arg_parser.py
api_dog_parser_v2/constants_and_enum.py
api_dog_parser_v2/parser.py
api_dog_parser_v2/parser_classes/__init__.py
api_dog_parser_v2/parser_classes/download_manager.py
api_dog_parser_v2/parser_classes/name_grabber.py
api_dog_parser_v2/parser_classes/parser_manager.py
api_dog_parser_v2/parser_classes/single_parser.py
images/how_to_1.png
images/how_to_2.png