Metadata-Version: 2.1
Name: api-dog-json-v2-parser
Version: 1.1.1
Summary: UNKNOWN
Home-page: https://github.com/benhacka/api-dog-json-v2-parser/
Author: rotten_meat
License: UNKNOWN
Download-URL: https://github.com/benhacka/api-dog-json-v2-parser/archive/v1.1.1.tar.gz
Platform: UNKNOWN
Requires-Python: >=3.6
